wildstruck/__init__.py
wildstruck/_boardData.py
wildstruck/_cli.py
wildstruck/_helper.py
wildstruck/_vec.py
wildstruck/_version.py
wildstruck/_pygparse/__init__.py
wildstruck/_pygparse/_cli.py
wildstruck/_pygparse/_flag.py
wildstruck/_pygparse/_repeatable.py
wildstruck/_pygparse/_sticky.py
wildstruck/_pygparse/_subcommand.py
wildstruck/_pygparse/parsers/__init__.py
wildstruck/_pygparse/parsers/_bool.py
wildstruck/_pygparse/parsers/_dict.py
wildstruck/_pygparse/parsers/_hex.py
wildstruck/_pygparse/parsers/_literal.py
wildstruck/_pygparse/parsers/_none.py
wildstruck/_slabelfish/__init__.py
wildstruck/_slabelfish/_assetsReader.py
wildstruck/_slabelfish/_decoder.py
wildstruck/_slabelfish/_encoder.py
wildstruck/_slabelfish/_model.py
wildstruck/_slabelfish/_utils.py
wildstruck/renderer/__init__.py
wildstruck/renderer/_renderer.py
wildstruck/renderer/_taleSpireAsset.py
wildstruck/renderer/_taleSpireSlab.py
wildstruck/renderer/config/__init__.py
wildstruck/renderer/config/_rendererConfig.py
wildstruck-3.0.1.dist-info/METADATA
wildstruck-3.0.1.dist-info/WHEEL
wildstruck-3.0.1.dist-info/entry_points.txt
wildstruck-3.0.1.dist-info/licenses/LICENSE
wildstruck-3.0.1.dist-info/RECORD
