Metadata-Version: 2.3
Name: wildstruck
Version: 3.0.1
Summary: Terrain generator for TaleSpire
Author: Fred Dufresne
License: Copyright © 2024 Fred Dufresne
Requires-Dist: pillow<11.1,>=11
Requires-Dist: pydantic<2.10,>=2.9
Requires-Dist: pyjson5<1.7,>=1.6
Requires-Dist: pyperclip<1.10,>=1.9
